LICENSE
MANIFEST.in
README.md
setup.py
libpythonpro/__init__.py
libpythonpro/github_api.py
libpythonprosfx.egg-info/PKG-INFO
libpythonprosfx.egg-info/SOURCES.txt
libpythonprosfx.egg-info/dependency_links.txt
libpythonprosfx.egg-info/not-zip-safe
libpythonprosfx.egg-info/requires.txt
libpythonprosfx.egg-info/top_level.txt